spiel/__init__.py
spiel/__main__.py
spiel/app.py
spiel/cli.py
spiel/constants.py
spiel/deck.py
spiel/demo/__init__.py
spiel/demo/demo.py
spiel/demo/tree.jpg
spiel/exceptions.py
spiel/py.typed
spiel/renderables/__init__.py
spiel/renderables/debug.py
spiel/renderables/image.py
spiel/screens/__init__.py
spiel/screens/deck.py
spiel/screens/help.py
spiel/screens/screen.py
spiel/screens/slide.py
spiel/screens/transition.py
spiel/slide.py
spiel/spiel.css
spiel/transitions/__init__.py
spiel/transitions/protocol.py
spiel/transitions/swipe.py
spiel/triggers.py
spiel/utils.py
spiel/widgets/__init__.py
spiel/widgets/bindings.py
spiel/widgets/fixed_slide.py
spiel/widgets/footer.py
spiel/widgets/minislides.py
spiel/widgets/slide.py
spiel/widgets/widget.py
spiel-0.5.1.dist-info/LICENSE
spiel-0.5.1.dist-info/METADATA
spiel-0.5.1.dist-info/WHEEL
spiel-0.5.1.dist-info/entry_points.txt
spiel-0.5.1.dist-info/RECORD
