Metadata-Version: 2.1
Name: spiel
Version: 0.5.1
Summary: A framework for building and presenting richly-styled presentations in your terminal using Python.
Home-page: https://github.com/JoshKarpel/spiel
License: MIT
Keywords: presentation,slides,tui,terminal
Author: JoshKarpel
Author-email: josh.karpel@gmail.com
Requires-Python: >=3.10,<4
Classifier: Development Status :: 3 - Alpha
Classifier: Environment :: Console
Classifier: Intended Audience :: Developers
Classifier: Intended Audience :: Education
Classifier: License :: OSI Approved :: MIT License
Classifier: Operating System :: MacOS
Classifier: Operating System :: Microsoft :: Windows
Classifier: Operating System :: Unix
Classifier: Programming Language :: Python :: 3
Classifier: Programming Language :: Python :: 3.10
Classifier: Programming Language :: Python :: 3.11
Classifier: Programming Language :: Python :: 3
Classifier: Programming Language :: Python :: 3 :: Only
Classifier: Programming Language :: Python :: 3.10
Classifier: Programming Language :: Python :: 3.11
Classifier: Topic :: Artistic Software
Classifier: Topic :: Multimedia :: Graphics :: Presentation
Classifier: Typing :: Typed
Requires-Dist: more-itertools (>=9)
Requires-Dist: pillow (>=8)
Requires-Dist: rich (>=13.2)
Requires-Dist: textual (==0.11.1)
Requires-Dist: typer (>=0.6)
Requires-Dist: watchfiles (>=0.18)
Project-URL: Documentation, https://www.spiel.how
Project-URL: Repository, https://github.com/JoshKarpel/spiel
